.gitignore
LICENSE.txt
README.md
setup.cfg
setup.py
pymeteosource/__init__.py
pymeteosource/api.py
pymeteosource/data.py
pymeteosource/errors.py
pymeteosource/request_handler.py
pymeteosource.egg-info/PKG-INFO
pymeteosource.egg-info/SOURCES.txt
pymeteosource.egg-info/dependency_links.txt
pymeteosource.egg-info/requires.txt
pymeteosource.egg-info/top_level.txt
pymeteosource/types/__init__.py
pymeteosource/types/endpoints.py
pymeteosource/types/icons.py
pymeteosource/types/langs.py
pymeteosource/types/sections.py
pymeteosource/types/tiers.py
pymeteosource/types/time_formats.py
pymeteosource/types/units.py
tests/__init__.py
tests/dst_changes_data.py
tests/sample_data.py
tests/test_api.py
tests/variables_list.py