Metadata-Version: 2.1
Name: pymeteosource
Version: 1.5.0
Summary: Meteosource API wrapper library
Home-page: https://github.com/Meteosource/pymeteosource/archive/v1.5.0.tar.gz
Author: Meteosource
Author-email: support@meteosource.com
License: MIT
Classifier: Environment :: Web Environment
Classifier: Intended Audience :: Developers
Classifier: Programming Language :: Python :: 3.6
Classifier: Topic :: Software Development :: Libraries :: Python Modules
Provides-Extra: pandas
License-File: LICENSE.txt
